__builtins__.pyi
_boot.pyi
_boot_fat.pyi
_onewire.pyi
_rp2.pyi
_thread.pyi
_uasyncio.pyi
array.pyi
binascii.pyi
cmath.pyi
collections.pyi
cryptolib.pyi
dht.pyi
ds18x20.pyi
errno.pyi
framebuf.pyi
gc.pyi
hashlib.pyi
heapq.pyi
io.pyi
json.pyi
logging.pyi
lwip.pyi
machine.pyi
math.pyi
micropython.pyi
mip.pyi
neopixel.pyi
network.pyi
ntptime.pyi
onewire.pyi
os.pyi
random.pyi
rp2.pyi
select.pyi
socket.pyi
ssl.pyi
struct.pyi
sys.pyi
time.pyi
uarray.pyi
uasyncio/__init__.pyi
uasyncio/core.pyi
uasyncio/event.pyi
uasyncio/funcs.pyi
uasyncio/lock.pyi
uasyncio/stream.pyi
uasyncio/task.pyi
ubinascii.pyi
ucollections.pyi
ucryptolib.pyi
uctypes.pyi
uerrno.pyi
uhashlib.pyi
uheapq.pyi
uio.pyi
ujson.pyi
umachine.pyi
uos.pyi
urandom.pyi
ure.pyi
urequests.pyi
uselect.pyi
usocket.pyi
ussl.pyi
ustruct.pyi
usys.pyi
utime.pyi
uwebsocket.pyi
uzlib.pyi
websocket.pyi
zlib.pyi
micropython_rp2_pico_w_stubs-1.20.0.post4.dist-info/LICENSE.md
micropython_rp2_pico_w_stubs-1.20.0.post4.dist-info/METADATA
micropython_rp2_pico_w_stubs-1.20.0.post4.dist-info/WHEEL
micropython_rp2_pico_w_stubs-1.20.0.post4.dist-info/RECORD
